df_qwerty/__init__.py
df_qwerty/conditions.py
df_qwerty/labels.py
df_qwerty/responses.py
df_qwerty/core/__init__.py
df_qwerty/core/actor.py
df_qwerty/core/context.py
df_qwerty/core/keywords.py
df_qwerty/core/normalization.py
df_qwerty/core/script.py
df_qwerty/core/types.py
tests/__init__.py
tests/test_actor.py
tests/test_conditions.py
tests/test_context.py
tests/test_examples.py
tests/test_labels.py
tests/test_normalization.py
tests/test_responses.py
tests/test_script.py
tests/utils.py
utils/__init__.py
utils/downgrade_patch.py
df_qwerty-0.9.0.dist-info/LICENSE
df_qwerty-0.9.0.dist-info/METADATA
df_qwerty-0.9.0.dist-info/WHEEL
df_qwerty-0.9.0.dist-info/top_level.txt
df_qwerty-0.9.0.dist-info/RECORD
