Metadata-Version: 2.1
Name: df-qwerty
Version: 0.9.0
Summary: The Dialog Flow Engine (DFE) allows you to write conversational services. The service is written by defining a special dialog graph that describes the behavior of the dialog service. The dialog graph contains the dialog script. DFE offers a specialized language (DSL) for quickly writing dialog graphs. You can use it in such services for writing skills for Amazon Alexa and etc, chat-bots for social networks, websites call-centers and etc.
Home-page: https://github.com/deepmipt/dialog_flow_engine
Author: Denis Kuznetsov
Author-email: kuznetsov.den.p@gmail.com
Keywords: chatbots
Classifier: Development Status :: 5 - Production/Stable
Classifier: Intended Audience :: Developers
Classifier: Topic :: Software Development :: Build Tools
Classifier: License :: OSI Approved :: Apache Software License
Classifier: Operating System :: OS Independent
Classifier: Programming Language :: Python :: 3
Classifier: Programming Language :: Python :: 3.6
Classifier: Programming Language :: Python :: 3.7
Classifier: Programming Language :: Python :: 3.8
Classifier: Programming Language :: Python :: 3.9
Classifier: Programming Language :: Python :: 3 :: Only
Requires-Python: >=3.6, <4
License-File: LICENSE
Requires-Dist: pydantic (>=1.8.2)
